{
  "items": [
    {
      "id": 1,
      "name": "Yogurt",
      "category": "Dairy",
      "isInCart": false
    },
    {
      "id": 2,
      "name": "Pomegranate",
      "category": "Produce",
      "isInCart": false
    },
    {
      "name": "fox",
      "category": "Produce",
      "isInCart": false,
      "id": 8
    },
    {
      "name": "zein",
      "category": "Dairy",
      "isInCart": false,
      "id": 10
    },
    {
      "name": "canvas",
      "category": "Dairy",
      "isInCart": false,
      "id": 11
    },
    {
      "name": "assignment",
      "category": "Dairy",
      "isInCart": false,
      "id": 12
    }
  ]
}